flask_sample/__init__.py
flask_sample/__main__.py
flask_sample/app.py
flask_sample/wsgi.py
flask_sample/static/bootstrap/4.4.1/css/bootstrap.css
flask_sample/static/bootstrap/4.4.1/js/bootstrap.js
flask_sample/static/custom/1.0/style.css
flask_sample/templates/index.html
flask_sample-0.4a4.dist-info/LICENSE
flask_sample-0.4a4.dist-info/METADATA
flask_sample-0.4a4.dist-info/WHEEL
flask_sample-0.4a4.dist-info/entry_points.txt
flask_sample-0.4a4.dist-info/top_level.txt
flask_sample-0.4a4.dist-info/RECORD
