Metadata-Version: 2.1
Name: flask-sample
Version: 0.4a4
Summary: A sample Flask app
Home-page: https://github.com/ph20/flask-sample
Author: Alexander Grynchuk
Author-email: agrynchuk@gmail.com
License: UNKNOWN
Project-URL: Bug Reports, https://github.com/ph20/flask-sample/issues
Project-URL: Source, https://github.com/ph20/flask-sample/
Keywords: sample setuptools development flask
Platform: UNKNOWN
Classifier: Development Status :: 3 - Alpha
Classifier: Intended Audience :: Developers
Classifier: Topic :: Software Development :: Build Tools
Classifier: License :: OSI Approved :: MIT License
Classifier: Programming Language :: Python :: 3
Classifier: Programming Language :: Python :: 3.5
Classifier: Programming Language :: Python :: 3.6
Classifier: Programming Language :: Python :: 3.7
Classifier: Programming Language :: Python :: 3.8
Classifier: Programming Language :: Python :: 3.9
Requires-Python: >=3.5
Requires-Dist: Flask (==2.0.1)
Requires-Dist: Jinja2 (==3.0.1)
Requires-Dist: Click (==8.0.1)
Provides-Extra: dev
Requires-Dist: wheel ; extra == 'dev'
Provides-Extra: gunicorn
Requires-Dist: gunicorn ; extra == 'gunicorn'
